iis_frida/__init__.py
iis_frida/model/__init__.py
iis_frida/model/common/__init__.py
iis_frida/model/common/calculator.py
iis_frida/utils/__init__.py
iis_kix-3.8.1.dist-info/METADATA
iis_kix-3.8.1.dist-info/WHEEL
iis_kix-3.8.1.dist-info/top_level.txt
iis_kix-3.8.1.dist-info/RECORD
