Metadata-Version: 2.4
Name: iis-kix
Version: 3.8.1
Summary: Example Python Module
Author-email: IT Services <pypi@iis.fraunhofer.de>
Project-URL: Homepage, https://www.iis.fraunhofer.de/
Project-URL: Bug Tracker, https://www.iis.fraunhofer.de/
Requires-Python: >=3.10
